[
{"name": "暗恋·橘生淮南", "author": "八月长安[著]", "call_number": "I247.57/5494"},
{"name": "Time series and panel data econometrics / First edition.", "author": "M. Hashem Pesaran.", "call_number": "F224.0/EN4"},
{"name": "杀死一只知更鸟.第2版", "author": "(美国) 哈珀·李著", "call_number": "I712.45/1231=2"},
{"name": "西窗法雨", "author": "刘星著", "call_number": "D909.1/3"},
{"name": "叫魂:1768年中国妖术大恐慌:the Chinese sorcery scare of 1768", "author": "(美) 孔飞力", "call_number": "B992.5/4"},
{"name": "今日店休:93岁旧书店主写给生活的情书", "author": "(日)坂本健一著", "call_number": "I313.65/187"},
{"name": "痛风的诊断与治疗", "author": "薛耀明，李晨钟主编", "call_number": "R589.7/4"},
{"name": "国境以南 太阳以西", "author": "(日)村上春树著", "call_number": "I313.45/356"},
{"name": "牛津初阶英汉双解词典", "author": "AngelaCrawley英语原版编辑", "call_number": "H316/255"},
{"name": "禁忌魔术", "author": "(日)东野圭吾著", "call_number": "I313.45/1119"},
{"name": "平凡的世界.第三部", "author": "路遥[著]", "call_number": "I247.5/663/7/V.3"},
{"name": "拉普拉斯的魔女", "author": "東野圭吾著", "call_number": "I313.45/1039"},
{"name": "小姨多鹤", "author": "严歌苓著", "call_number": "I247.57/3750"},
{"name": "芳华", "author": "严歌苓著", "call_number": "I247.5/3791"},
{"name": "我是猫:绘图本", "author": "(日) 夏目漱石著", "call_number": "I313.44/18"},
{"name": "越秀史稿", "author": "广州市越秀区人民政府地方志办公室, 广州市越秀区政协学习和文史委员会主编", "call_number": "K296.51/89"},
{"name": "时间简史:插图本", "author": "史蒂芬·霍金", "call_number": "P159-49/4"},
{"name": "美味花果茶", "author": "马丽娜,周亚娟著", "call_number": "TS272.5/27"},
{"name": "毛泽东传.第2版", "author": "中共中央文献研究室编", "call_number": "A751/28"},
{"name": "假面饭店", "author": "(日)东野圭吾著", "call_number": "I313.45/864"},
{"name": "造彩虹的人", "author": "东野圭吾[日]", "call_number": "I313.45/1075"},
{"name": "国富论.上", "author": "(英) 亚当斯密著", "call_number": "F091.33/46/V.1"},
{"name": "解忧杂货店", "author": "(日)东野圭吾著", "call_number": "I313.45/735"},
{"name": "专家诊治痛风", "author": "主编潘新", "call_number": "R4-49/16"},
{"name": "翻译问题探讨", "author": "Peter Newmark", "call_number": "H059/36"},
{"name": "老中医教中老年怎么吃", "author": "良石, 刘慧滢主编", "call_number": "R153.3/17"},
{"name": "濒死之眼", "author": "(日) 东野圭吾著", "call_number": "I313.45/1074"},
{"name": "局外人", "author": "(法) 阿尔贝·加缪著", "call_number": "I565.45/241"},
{"name": "局外人", "author": "(法) 阿尔贝·加缪著", "call_number": "I565.45/283"},
{"name": "百年美文:1900-2000,读书卷.青春阅读版", "author": "季羡林主编", "call_number": "I266/360-2"},
{"name": "了不起的盖茨比", "author": "(美) 菲茨杰拉德著", "call_number": "I712.45/921"},
{"name": "乖，摸摸头", "author": "大冰[著]", "call_number": "I247.81/5"},
{"name": "浮休", "author": "(日) 渡边淳一著", "call_number": "I313.45/932"},
{"name": "十一字杀人", "author": "(日)东野圭吾著", "call_number": "I313.45/544"},
{"name": "第七天", "author": "余华著", "call_number": "I247.5/3527"},
{"name": "在细雨中呼喊", "author": "余华[著]", "call_number": "I247.57/2702"},
{"name": "巨流河", "author": "齐邦媛著", "call_number": "I247.5/3440"},
{"name": "纸牌屋", "author": "(英) 迈克尔·道布斯著", "call_number": "I561.45/594"},
{"name": "2018", "author": "刘慈欣", "call_number": "I247.7/1728"},
{"name": "萤火虫小巷", "author": "(美)克莉丝汀·汉娜著", "call_number": "I712.45/1476"},
{"name": "白马山庄杀人事件", "author": "东野圭吾著", "call_number": "I313.45/849"},
{"name": "恋恋笔记本", "author": "(美)尼古拉斯·斯帕克思著", "call_number": "I712.45/1859"},
{"name": "且听风吟", "author": "村上春树著", "call_number": "I313.45/93/2"},
{"name": "小团圆", "author": "张爱玲,", "call_number": "I246.57/79"},
{"name": "沉睡的森林", "author": "(日)东野圭吾著", "call_number": "I313.45/855"},
{"name": "恶意.第2版", "author": "(日) 东野圭吾著", "call_number": "I313.45/563=2"},
{"name": "毕业", "author": "(日) 东野圭吾著", "call_number": "I313.45/554"},
{"name": "沉默的大多数", "author": "王小波著", "call_number": "I267.1/1853"},
{"name": "她和他", "author": "(法)马克·李维(Marc Levy)著", "call_number": "I565.45/404"},
{"name": "亲爱的安德烈", "author": "龙应台, 安德烈合著", "call_number": "I267.5/125"},
{"name": "没有凶手的杀人夜", "author": "(日) 东野圭吾著", "call_number": "I313.45/516"},
{"name": "半落", "author": "(日)横山秀夫著", "call_number": "I313.45/1069"},
{"name": "那时的某人", "author": "(日)东野圭吾著", "call_number": "I313.45/1060"},
{"name": "放学后", "author": "(日) 东野圭吾著", "call_number": "I313.45/617"},
{"name": "花与爱丽丝杀人事件", "author": "(日)乙一著", "call_number": "I313.456/93"},
{"name": "愿你的青春不负年华:小微创业领跑者许磊", "author": "刘芸畅著", "call_number": "K825.38/277"},
{"name": "从0到无穷，数学如何改变了世界", "author": "克里斯·韦林著", "call_number": "O11-49/8"},
{"name": "基础有机化学.上册.2版", "author": "邢其毅等编", "call_number": "O62/40=2/V.1"},
{"name": "广东凉茶.修订本", "author": "秦艳芬编著", "call_number": "R289.5/28=2"},
{"name": "百变营养粥", "author": "犀文图书编著", "call_number": "TS972.137/19"},
{"name": "毛泽东选集.第一卷.2版", "author": "毛泽东著", "call_number": "A41/4=2/V.1"},
{"name": "毛泽东选集.第二卷.2版", "author": "毛泽东著", "call_number": "A41/4=2/V.2"},
{"name": "一九八四", "author": "(英) 乔治·奥威尔著", "call_number": "I561.45/12-2"},
{"name": "最强大脑之脑力激荡术:神奇的脑力激荡术", "author": "哈里·洛拉尼著", "call_number": "B848.5/57"},
{"name": "做不可能的事:变不可能为可能的25法则", "author": "(美) 帕特里克·贝特－戴维著", "call_number": "B848.4-49/802"},
{"name": "博弈论的诡计.Ⅱ:日常生活中的博弈策略.插图本", "author": "王春永编著", "call_number": "C934-49/15/V.2"},
{"name": "微观经济学习题集", "author": "张顺主编", "call_number": "F016-44/18"},
{"name": "养生的智慧", "author": "杨东野编著", "call_number": "R212/162"},
{"name": "七八分饱的健康人生", "author": "赵熠宸主编", "call_number": "R151/87"},
{"name": "牛津高阶英汉双解词典.4版", "author": "霍恩比(A.S. Hornby)原著", "call_number": "H316/148=4"},
{"name": "濒死之眼", "author": "(日) 东野圭吾著", "call_number": "I313.456/7-2"},
{"name": "拿起手机拍大片:跟摄影师学手机摄影技巧", "author": "郑壬杰著", "call_number": "J41/439"},
{"name": "设计思维与创意.第2版", "author": "伍斌, 曹利, 孔祥国著", "call_number": "J06/369=2"},
{"name": "两岸新编中国近代史,民国卷", "author": "王建朗，黄克武主编", "call_number": "K25/157"},
{"name": "土壤学", "author": "王果主编", "call_number": "S15/91"},
{"name": "猪的信号:观察，思考和行动", "author": "(荷) 杨浩森著", "call_number": "S828.4/39"},
{"name": "作物栽培学", "author": "胡立勇, 丁艳锋主编", "call_number": "S31/24"},
{"name": "上瘾:让用户养成使用习惯的四大产品逻辑:how to build habit-forming products", "author": "(美) 尼尔·埃亚尔, (美) 瑞安·胡佛著", "call_number": "TB472/383"},
{"name": "Access 2010数据库实用教程", "author": "主编王红", "call_number": "TP311.138/1293"},
{"name": "J2EE项目开发与设计.第2版", "author": "彭灿华, 韦晓敏, 魏士伟主编", "call_number": "TP312/4948=2"},
{"name": "锋利的jQuery.2版", "author": "单东林，张晓菲，魏然编著", "call_number": "TP312/3618=2"},
{"name": "Python数据分析与挖掘实战", "author": "张良均 ... [等] 著", "call_number": "TP311.56/740"},
{"name": "Node.js进阶之路", "author": "尤嘉编著", "call_number": "TP312/4998"},
{"name": "简单易学 玩转Arduino", "author": "孙德军主编", "call_number": "TP368.1/442"},
{"name": "PHP+MySQL+Dreamweaver网站建设", "author": "李晓斌等编著", "call_number": "TP312/4885"},
{"name": "怪诞心理学.2,不可思议的心理操控,why we see what isn't there.新版", "author": "(英)理查德·怀斯曼著", "call_number": "B84/308/V.2"},
{"name": "中国哲学简史", "author": "冯友兰著", "call_number": "B2/252"},
{"name": "论语今读", "author": "李泽厚著", "call_number": "B222.22/24"},
{"name": "谈美", "author": "朱光潜著", "call_number": "B83/203"},
{"name": "摩西五经", "author": "冯象译注", "call_number": "B971/71"},
{"name": "认知突围:做复杂时代的明白人", "author": "蔡垒磊著", "call_number": "B842.1/70"},
{"name": "乌合之众:大众心理研究", "author": "(法) 古斯塔夫·勒庞著", "call_number": "C912.64/10"},
{"name": "公共行政与公共事务", "author": "(美)尼古拉斯·亨利著", "call_number": "D035/97"},
{"name": "广州农村发展报告.2013", "author": "李江涛，汤锦华主编", "call_number": "F327.651/5/2013"},
{"name": "傲慢与偏见", "author": "(英)J. 奥斯汀(J. Austen)原著", "call_number": "H319.4/4191"},
{"name": "呼啸山庄", "author": "(英)E. 勃朗特(E. Bronte)原著", "call_number": "H319.4/4192"},
{"name": "GRE核心词汇考法精析", "author": "陈琦主编", "call_number": "H313/572"},
{"name": "公共营养学", "author": "主编李菊花", "call_number": "R151/58"},
{"name": "华为管理法:任正非的企业管理心得", "author": "黄志伟编著", "call_number": "F632.765.3/49"},
{"name": "众筹:互联网金融的下一个风口", "author": "陈晓暾, 白帆, 陈英编著", "call_number": "F830.45/77"}
]